cs/env.py
cs.env-20230407.dist-info/METADATA
cs.env-20230407.dist-info/WHEEL
cs.env-20230407.dist-info/top_level.txt
cs.env-20230407.dist-info/RECORD
